IC23005UNO/__init__.py
IC23005UNO/sistemas_lineales.py
IC23005UNO/sistemas_no_lineales.py
ic23005uno-1.0.1.dist-info/licenses/LICENSE
ic23005uno-1.0.1.dist-info/METADATA
ic23005uno-1.0.1.dist-info/WHEEL
ic23005uno-1.0.1.dist-info/top_level.txt
ic23005uno-1.0.1.dist-info/RECORD
