Metadata-Version: 2.4
Name: IC23005UNO
Version: 1.0.1
Summary: Librería para resolver ecuaciones lineales y no lineales con diferentes metodos.
Author-email: Erick Iraheta <ic23005@ues.edu.sv>
Maintainer-email: Erick Iraheta <ic23005@ues.edu.sv>
License: ===============================================================================================
Project-URL: Repository, https://github.com/ic23005/CDA135/tree/main/IC23005UNO
Keywords: numerical methods,linear algebra,root finding,scipy,numpy,math
Classifier: License :: OSI Approved :: MIT License
Classifier: Programming Language :: Python :: 3.7
Classifier: Programming Language :: Python :: 3.8
Classifier: Programming Language :: Python :: 3.9
Classifier: Programming Language :: Python :: 3.10
Classifier: Programming Language :: Python :: 3.11
Classifier: Programming Language :: Python :: 3.12
Classifier: Programming Language :: Python :: 3.13
Classifier: Operating System :: OS Independent
Classifier: Intended Audience :: Developers
Classifier: Intended Audience :: Science/Research
Classifier: Topic :: Scientific/Engineering :: Mathematics
Classifier: Topic :: Software Development :: Libraries :: Python Modules
Requires-Python: >=3.7
License-File: LICENSE
Requires-Dist: numpy>=1.18
Dynamic: license-file
